geocam/controller.py
geocam-0.0.1.dist-info/LICENSE
geocam-0.0.1.dist-info/METADATA
geocam-0.0.1.dist-info/WHEEL
geocam-0.0.1.dist-info/top_level.txt
geocam-0.0.1.dist-info/RECORD
